panamaram/__init__.py
panamaram/main.py
panamaram/assets/__init__.py
panamaram/assets/icon.ico
panamaram/assets/icon.png
panamaram/auth/__init__.py
panamaram/auth/auth.py
panamaram/db/__init__.py
panamaram/db/bill_manager.py
panamaram/db/db_manager.py
panamaram/db/expense_manager.py
panamaram/db/income_manager.py
panamaram/db/recurring_income_manager.py
panamaram/db/recurring_manager.py
panamaram/ui/__init__.py
panamaram/ui/bill_form.py
panamaram/ui/bill_table.py
panamaram/ui/currency_chooser.py
panamaram/ui/dashboard.py
panamaram/ui/expense_form.py
panamaram/ui/expense_table.py
panamaram/ui/income_form.py
panamaram/ui/income_table.py
panamaram/ui/main_window.py
panamaram/ui/reports.py
panamaram/utils/__init__.py
panamaram/utils/key_manager.py
panamaram/utils/path_utils.py
panamaram/utils/secure_field_utils.py
panamaram/utils/secure_file_utils.py
panamaram/utils/smart_suggestions.py
panamaram/worker/__init__.py
panamaram/worker/worker_unlock.py
panamaram-1.0.0.dist-info/licenses/LICENSE
panamaram-1.0.0.dist-info/METADATA
panamaram-1.0.0.dist-info/WHEEL
panamaram-1.0.0.dist-info/entry_points.txt
panamaram-1.0.0.dist-info/top_level.txt
panamaram-1.0.0.dist-info/RECORD
