Metadata-Version: 2.4
Name: panamaram
Version: 1.0.0
Summary: Panamaram Personal Finance Expense Tracker
Author-email: Manikandan D <manikandan@due.im>
License: MIT License
Project-URL: Homepage, https://due.im/panamaram/
Project-URL: Repository, https://github.com/manikandancode/Panamaram
Project-URL: BugTracker, https://github.com/manikandancode/Panamaram/issues
Keywords: personal finance,expense tracker,finance,expense,income tracker
Classifier: Development Status :: 5 - Production/Stable
Classifier: Intended Audience :: End Users/Desktop
Classifier: Intended Audience :: Developers
Classifier: License :: OSI Approved :: MIT License
Classifier: Programming Language :: Python :: 3
Classifier: Programming Language :: Python :: 3.13
Classifier: Operating System :: OS Independent
Classifier: Topic :: Software Development :: Libraries :: Application Frameworks
Classifier: Topic :: Office/Business :: Financial :: Accounting
Requires-Python: >=3.13
License-File: LICENSE
Requires-Dist: appdirs==1.4.4
Requires-Dist: cffi==1.17.1
Requires-Dist: contourpy==1.3.2
Requires-Dist: cryptography==45.0.5
Requires-Dist: cycler==0.12.1
Requires-Dist: defusedxml==0.7.1
Requires-Dist: et_xmlfile==2.0.0
Requires-Dist: fonttools==4.59.0
Requires-Dist: fpdf2==2.8.3
Requires-Dist: kiwisolver==1.4.8
Requires-Dist: matplotlib==3.10.3
Requires-Dist: numpy==2.3.1
Requires-Dist: openpyxl==3.1.5
Requires-Dist: packaging==25.0
Requires-Dist: pillow==11.3.0
Requires-Dist: pyAesCrypt==6.1.1
Requires-Dist: pycparser==2.22
Requires-Dist: pyparsing==3.2.3
Requires-Dist: PySide6==6.9.1
Requires-Dist: PySide6_Addons==6.9.1
Requires-Dist: PySide6_Essentials==6.9.1
Requires-Dist: python-dateutil==2.9.0.post0
Requires-Dist: shiboken6==6.9.1
Requires-Dist: six==1.17.0
Dynamic: license-file
